{
  "animateLoading": true,
  "borderRadius": "{{appsmith.theme.borderRadius.appBorderRadius}}",
  "bottomRow": 17,
  "dynamicBindingPathList": [
    {
      "key": "truncateButtonColor"
    },
    {
      "key": "fontFamily"
    },
    {
      "key": "borderRadius"
    },
    {
      "key": "text"
    }
  ],
  "dynamicHeight": "AUTO_HEIGHT",
  "fontFamily": "{{appsmith.theme.fontFamily.appFont}}",
  "fontSize": "1rem",
  "fontStyle": "BOLD",
  "isLoading": false,
  "isVisible": true,
  "key": "4rqpkp2lkc",
  "leftColumn": 23,
  "maxDynamicHeight": 9000,
  "minDynamicHeight": 4,
  "minWidth": 450,
  "mobileBottomRow": 16,
  "mobileLeftColumn": 23,
  "mobileRightColumn": 39,
  "mobileTopRow": 12,
  "needsErrorInfo": false,
  "originalBottomRow": 16,
  "originalTopRow": 12,
  "overflow": "NONE",
  "parentColumnSpace": 13.0625,
  "parentId": "0",
  "parentRowSpace": 10,
  "renderMode": "CANVAS",
  "responsiveBehavior": "fill",
  "rightColumn": 39,
  "shouldTruncate": false,
  "text": "Hello {{appsmith.user.name || appsmith.user.email}}",
  "textAlign": "LEFT",
  "textColor": "#231F20",
  "topRow": 12,
  "truncateButtonColor": "{{appsmith.theme.colors.primaryColor}}",
  "type": "TEXT_WIDGET",
  "version": 1,
  "widgetId": "3ed6gwxzz3",
  "widgetName": "Text1"
}